plantdb/client/__init__.py
plantdb/client/plantdb_client.py
plantdb/client/rest_api.py
plantdb/client/sync.py
plantdb/client/cli/__init__.py
plantdb/client/cli/fsdb_rest_api_sync.py
plantdb/client/cli/fsdb_sync.py
plantdb/client/sync_app/app.py
plantdb/client/sync_app/assets/custom.css
plantdb_client-0.14.5.dist-info/METADATA
plantdb_client-0.14.5.dist-info/WHEEL
plantdb_client-0.14.5.dist-info/entry_points.txt
plantdb_client-0.14.5.dist-info/top_level.txt
plantdb_client-0.14.5.dist-info/RECORD
