Metadata-Version: 2.4
Name: plantdb.client
Version: 0.14.5
Summary: Client-side database library for the ROMI plant database ecosystem.
Author-email: Peter Hanappe <peter.hanappe@sony.com>, Timothée Wintz <timothee@timwin.fr>, Nabil Ait Taleb <mohamednabil.aittaleb@sony.com>, Arthur Luciani <arthur.luciani@ens-lyon.fr>
Maintainer-email: Jonathan Legrand <jonathan.legrand@ens-lyon.fr>
License: LGPL-3.0-or-later
Project-URL: homepage, https://romi-project.eu/
Project-URL: documentation, https://docs.romi-project.eu/plant_imager/
Project-URL: source, https://github.com/romi/plantdb
Project-URL: issues, https://github.com/romi/plantdb/issues
Keywords: Robotics for Microfarms,ROMI,Plant Phenotyping,Scientific Database,Data Management,REST API
Classifier: Programming Language :: Python :: 3
Classifier: Development Status :: 4 - Beta
Classifier: Intended Audience :: Science/Research
Classifier: Topic :: Database
Classifier: Topic :: Scientific/Engineering :: Bio-Informatics
Classifier: Topic :: Software Development :: Libraries :: Python Modules
Classifier: Operating System :: OS Independent
Classifier: Natural Language :: English
Requires-Python: >=3.8
Requires-Dist: plantdb.commons
Requires-Dist: requests
Requires-Dist: tqdm
Requires-Dist: urllib3
Provides-Extra: sync
Requires-Dist: dash; extra == "sync"
Requires-Dist: dash-bootstrap-components; extra == "sync"
Requires-Dist: paramiko; extra == "sync"
